anno3d/__init__.py
anno3d/annofab/__init__.py
anno3d/annofab/client.py
anno3d/annofab/constant.py
anno3d/annofab/model.py
anno3d/annofab/project.py
anno3d/annofab/specifiers/__init__.py
anno3d/annofab/specifiers/extended_specs_label_specifiers_v1.py
anno3d/annofab/specifiers/label_specifiers.py
anno3d/annofab/specifiers/metadata_label_specifiers.py
anno3d/annofab/specifiers/project_specifiers.py
anno3d/annofab/specifiers/utils.py
anno3d/annofab/task.py
anno3d/annofab/uploader.py
anno3d/app.py
anno3d/calib_loader.py
anno3d/file_paths_loader.py
anno3d/kitti/__init__.py
anno3d/kitti/calib.py
anno3d/kitti/camera_horizontal_fov_provider.py
anno3d/kitti/scene_uploader.py
anno3d/model/__init__.py
anno3d/model/annotation_area.py
anno3d/model/common.py
anno3d/model/file_paths.py
anno3d/model/frame.py
anno3d/model/image.py
anno3d/model/input_files.py
anno3d/model/kitti_label.py
anno3d/model/label.py
anno3d/model/preset_cuboids.py
anno3d/model/project_specs_meta.py
anno3d/model/scene.py
anno3d/simple_data_uploader.py
anno3d/supplementary_id.py
anno3d/util/__init__.py
anno3d/util/modifier.py
anno3d/util/type_util.py
anno3d/util/value_provider.py
annofab_3dpc_editor_cli-0.4.1.dist-info/METADATA
annofab_3dpc_editor_cli-0.4.1.dist-info/WHEEL
annofab_3dpc_editor_cli-0.4.1.dist-info/entry_points.txt
annofab_3dpc_editor_cli-0.4.1.dist-info/licenses/LICENSE
annofab_3dpc_editor_cli-0.4.1.dist-info/RECORD
