Metadata-Version: 2.4
Name: annofab-3dpc-editor-cli
Version: 0.4.1
Summary: Annofabの3次元プロジェクトを操作するためのCLIです。
License: MIT
License-File: LICENSE
Author: Kurusugawa Computer Inc.
Requires-Python: >=3.9,<4.0
Classifier: Environment :: Console
Classifier: Intended Audience :: Developers
Classifier: License :: OSI Approved :: MIT License
Classifier: Operating System :: OS Independent
Classifier: Programming Language :: Python :: 3
Classifier: Programming Language :: Python :: 3.9
Classifier: Programming Language :: Python :: 3.10
Classifier: Programming Language :: Python :: 3.11
Classifier: Programming Language :: Python :: 3.12
Classifier: Programming Language :: Python :: 3.13
Classifier: Programming Language :: Python :: 3.14
Classifier: Topic :: Utilities
Requires-Dist: annofabapi (>=1.3,<2.0)
Requires-Dist: boto3 (>=1.17.20,<2.0.0)
Requires-Dist: botocore (>=1.42.13,<2.0.0)
Requires-Dist: dataclasses-json (>=0.5.7,<1)
Requires-Dist: fire (>=0.3.1,<1)
Requires-Dist: more-itertools (>=8.5.0)
Requires-Dist: numpy (>=1.23,<3)
Requires-Dist: scipy (>=1.9.0,<2.0.0)
Project-URL: Repository, https://github.com/kurusugawa-computer/annofab-3dpc-editor-cli
